{
  "carvers": [
    "minecraft:cave",
    "minecraft:cave_extra_underground",
    "minecraft:canyon"
  ],
  "downfall": 0.8,
  "effects": {
    "fog_color": 11457020,
    "grass_color_modifier": "dark_forest",
    "mood_sound": {
      "block_search_extent": 8,
      "offset": 2.0,
      "sound": "minecraft:ambient.cave",
      "tick_delay": 6000
    },
    "music": [],
    "music_volume": 0.0,
    "sky_color": 5479112,
    "water_color": 2983612,
    "water_fog_color": 198410
  },
  "features": [
    [],
    [
      "minecraft:lake_lava_underground"
    ],
    [
      "minecraft:amethyst_geode"
    ],
    [
      "minecraft:monster_room",
      "minecraft:monster_room_deep"
    ],
    [],
    [
      "clifftree:stone_cliff"
    ],
    [
      "minecraft:ore_dirt",
      "minecraft:ore_gravel",
      "minecraft:ore_granite_upper",
      "minecraft:ore_granite_lower",
      "minecraft:ore_diorite_upper",
      "minecraft:ore_diorite_lower",
      "minecraft:ore_andesite_upper",
      "minecraft:ore_andesite_lower",
      "minecraft:ore_tuff",
      "minecraft:ore_coal_upper",
      "minecraft:ore_coal_lower",
      "minecraft:ore_iron_upper",
      "minecraft:ore_iron_middle",
      "minecraft:ore_iron_small",
      "minecraft:ore_gold",
      "minecraft:ore_gold_lower",
      "minecraft:ore_redstone",
      "minecraft:ore_redstone_lower",
      "minecraft:ore_diamond",
      "minecraft:ore_diamond_medium",
      "minecraft:ore_diamond_large",
      "minecraft:ore_diamond_buried",
      "minecraft:ore_lapis",
      "minecraft:ore_lapis_buried",
      "minecraft:ore_copper",
      "minecraft:underwater_magma",
      "minecraft:disk_sand",
      "minecraft:disk_clay",
      "minecraft:disk_gravel"
    ],
    [],
    [
      "minecraft:spring_water"
    ],
    [
      "minecraft:glow_lichen",
      "minecraft:pale_garden_vegetation",
      "vanilluxe:dark_moss_patch",
      "minecraft:pale_garden_flowers",
      "minecraft:flower_pale_garden",
      "minecraft:patch_grass_forest",
      "minecraft:brown_mushroom_old_growth",
      "minecraft:red_mushroom_old_growth",
      "minecraft:brown_mushroom_normal",
      "minecraft:red_mushroom_normal",
      "clifftree:dark_forest_mushroom",
      "minecraft:patch_sugar_cane",
      "minecraft:patch_pumpkin",
      "clifftree:forest_fern"
    ],
    [
      "clifftree:extra_gold_remove",
      "clifftree:extra_emerald_remove",
      "minecraft:freeze_top_layer"
    ]
  ],
  "has_precipitation": true,
  "spawn_costs": {
    "minecraft:spider": {
      "energy_budget": 0.5,
      "charge": 0.7
    },
    "minecraft:zombie": {
      "energy_budget": 0.5,
      "charge": 0.7
    },
    "minecraft:zombie_villager": {
      "energy_budget": 0.5,
      "charge": 0.7
    },
    "minecraft:skeleton": {
      "energy_budget": 0.5,
      "charge": 0.7
    },
    "minecraft:creeper": {
      "energy_budget": 0.5,
      "charge": 0.7
    },
    "minecraft:enderman": {
      "energy_budget": 0.5,
      "charge": 0.7
    },
    "minecraft:witch": {
      "energy_budget": 0.5,
      "charge": 0.7
    }
  },
  "spawners": {
    "ambient": [
      {
        "type": "minecraft:bat",
        "maxCount": 8,
        "minCount": 8,
        "weight": 10
      }
    ],
    "axolotls": [],
    "creature": [],
    "misc": [],
    "monster": [
      {
        "type": "minecraft:spider",
        "maxCount": 4,
        "minCount": 4,
        "weight": 100
      },
      {
        "type": "minecraft:zombie",
        "maxCount": 2,
        "minCount": 2,
        "weight": 95
      },
      {
        "type": "minecraft:zombie_villager",
        "maxCount": 1,
        "minCount": 1,
        "weight": 5
      },
      {
        "type": "minecraft:skeleton",
        "maxCount": 1,
        "minCount": 1,
        "weight": 80
      },
      {
        "type": "minecraft:creeper",
        "maxCount": 1,
        "minCount": 1,
        "weight": 20
      },
      {
        "type": "minecraft:slime",
        "maxCount": 4,
        "minCount": 4,
        "weight": 100
      },
      {
        "type": "minecraft:enderman",
        "maxCount": 4,
        "minCount": 1,
        "weight": 20
      },
      {
        "type": "minecraft:witch",
        "maxCount": 1,
        "minCount": 1,
        "weight": 10
      }
    ],
    "underground_water_creature": [
      {
        "type": "minecraft:glow_squid",
        "maxCount": 6,
        "minCount": 4,
        "weight": 10
      }
    ],
    "water_ambient": [],
    "water_creature": []
  },
  "temperature": 0.7
}