{
  "elements": [
    {
      "element": {
        "element_type": "minecraft:single_pool_element",
        "location": "minecraft:witch_hut/brewingstand_1",
        "processors": {
          "processors": []
        },
        "projection": "rigid"
      },
      "weight": 1
    },
    {
      "element": {
        "element_type": "minecraft:single_pool_element",
        "location": "minecraft:witch_hut/brewingstand_2",
        "processors": {
          "processors": []
        },
        "projection": "rigid"
      },
      "weight": 1
    },
    {
      "element": {
        "element_type": "minecraft:single_pool_element",
        "location": "minecraft:witch_hut/brewingstand_3",
        "processors": {
          "processors": []
        },
        "projection": "rigid"
      },
      "weight": 1
    },
    {
      "element": {
        "element_type": "minecraft:single_pool_element",
        "location": "minecraft:witch_hut/brewingstand_4",
        "processors": {
          "processors": []
        },
        "projection": "rigid"
      },
      "weight": 1
    },
    {
      "element": {
        "element_type": "minecraft:single_pool_element",
        "location": "minecraft:witch_hut/brewingstand_5",
        "processors": {
          "processors": []
        },
        "projection": "rigid"
      },
      "weight": 1
    },
    {
      "element": {
        "element_type": "minecraft:single_pool_element",
        "location": "minecraft:witch_hut/brewingstand_6",
        "processors": {
          "processors": []
        },
        "projection": "rigid"
      },
      "weight": 1
    }
  ],
  "fallback": "minecraft:empty"
}